grid2op/Parameters.py
grid2op/__init__.py
grid2op/_create_test_suite.py
grid2op/_glop_platform_info.py
grid2op/command_line.py
grid2op/dtypes.py
grid2op/main.py
grid2op/typing_variables.py
grid2op/Action/__init__.py
grid2op/Action/_backendAction.py
grid2op/Action/actionSpace.py
grid2op/Action/baseAction.py
grid2op/Action/completeAction.py
grid2op/Action/dispatchAction.py
grid2op/Action/dontAct.py
grid2op/Action/playableAction.py
grid2op/Action/powerlineChangeAction.py
grid2op/Action/powerlineChangeAndDispatchAction.py
grid2op/Action/powerlineChangeDispatchAndStorageAction.py
grid2op/Action/powerlineSetAction.py
grid2op/Action/powerlineSetAndDispatchAction.py
grid2op/Action/serializableActionSpace.py
grid2op/Action/topologyAction.py
grid2op/Action/topologyAndDispatchAction.py
grid2op/Action/topologyChangeAction.py
grid2op/Action/topologyChangeAndDispatchAction.py
grid2op/Action/topologySetAction.py
grid2op/Action/topologySetAndDispatchAction.py
grid2op/Action/voltageOnlyAction.py
grid2op/Action/_BackendAction/__init__.py
grid2op/Agent/__init__.py
grid2op/Agent/agentWithConverter.py
grid2op/Agent/alertAgent.py
grid2op/Agent/baseAgent.py
grid2op/Agent/deltaRedispatchRandomAgent.py
grid2op/Agent/doNothing.py
grid2op/Agent/fromActionsListAgent.py
grid2op/Agent/greedyAgent.py
grid2op/Agent/mlAgent.py
grid2op/Agent/oneChangeThenNothing.py
grid2op/Agent/powerlineSwitch.py
grid2op/Agent/randomAgent.py
grid2op/Agent/recoPowerLinePerArea.py
grid2op/Agent/recoPowerlineAgent.py
grid2op/Agent/topologyGreedy.py
grid2op/Backend/__init__.py
grid2op/Backend/backend.py
grid2op/Backend/educPandaPowerBackend.py
grid2op/Backend/name_attributes.py
grid2op/Backend/pandaPowerBackend.py
grid2op/Chronics/GSFFWFWM.py
grid2op/Chronics/Settings_5busExample.py
grid2op/Chronics/Settings_L2RPN2019.py
grid2op/Chronics/Settings_case14_realistic.py
grid2op/Chronics/Settings_case14_redisp.py
grid2op/Chronics/Settings_case14_test.py
grid2op/Chronics/__init__.py
grid2op-1.12.1.dist-info/licenses/AUTHORS.txt
grid2op-1.12.1.dist-info/licenses/LICENSE.md
grid2op-1.12.1.dist-info/METADATA
grid2op-1.12.1.dist-info/WHEEL
grid2op-1.12.1.dist-info/entry_points.txt
grid2op-1.12.1.dist-info/top_level.txt
grid2op-1.12.1.dist-info/RECORD
