Metadata-Version: 2.4
Name: grid2op
Version: 1.12.1
Summary: An gymnasium compatible environment to model sequential decision making for powersystems
Author-email: DONNOT Benjamin <benjamin.donnot@rte-france.com>
Maintainer-email: DONNOT Benjamin <benjamin.donnot@rte-france.com>
Project-URL: Homepage, https://github.com/Grid2op
Project-URL: Documentation, https://grid2op.readthedocs.io/
Project-URL: Repository, https://github.com/Grid2op/grid2op
Project-URL: Bug Tracker, https://github.com/Grid2op/grid2op/issues
Project-URL: Changelog, https://github.com/Grid2op/grid2op/blob/master/CHANGELOG.rst
Keywords: ML,powergrid,optmization,RL,power-systems
Classifier: Development Status :: 4 - Beta
Classifier: Programming Language :: Python
Classifier: Programming Language :: Python :: 3.8
Classifier: Programming Language :: Python :: 3.9
Classifier: Programming Language :: Python :: 3.10
Classifier: Programming Language :: Python :: 3.11
Classifier: Programming Language :: Python :: 3.12
Classifier: Programming Language :: Python :: 3.13
Classifier: Intended Audience :: Developers
Classifier: Intended Audience :: Education
Classifier: Intended Audience :: Science/Research
Classifier: Natural Language :: English
Classifier: Operating System :: MacOS
Classifier: Operating System :: Microsoft :: Windows
Classifier: Operating System :: POSIX
Classifier: Topic :: Scientific/Engineering
Requires-Python: >=3.8
License-File: LICENSE.md
License-File: AUTHORS.txt
Requires-Dist: scipy>=1.4.1
Requires-Dist: pandas<3,>=1.0.3
Requires-Dist: pandapower>=3.1.1; python_version >= "3.9"
Requires-Dist: numpy
Requires-Dist: scipy
Requires-Dist: tqdm>=4.45.0
Requires-Dist: networkx>=2.4
Requires-Dist: requests>=2.23.0
Requires-Dist: packaging
Requires-Dist: typing_extensions
Requires-Dist: orderly_set<5.4.0; python_version <= "3.8"
Requires-Dist: importlib_resources; python_version <= "3.8"
Requires-Dist: pandapower<3; python_version <= "3.8"
Requires-Dist: numpy<2; python_version <= "3.8"
Requires-Dist: scipy<1.14; python_version <= "3.8"
Provides-Extra: optional
Requires-Dist: nbformat>=5.0.4; extra == "optional"
Requires-Dist: jupyter-client>=6.1.0; extra == "optional"
Requires-Dist: numba>=0.48.0; extra == "optional"
Requires-Dist: matplotlib>=3.2.1; extra == "optional"
Requires-Dist: plotly>=4.5.4; extra == "optional"
Requires-Dist: seaborn>=0.10.0; extra == "optional"
Requires-Dist: imageio>=2.8.0; extra == "optional"
Requires-Dist: pygifsicle>=1.0.1; extra == "optional"
Requires-Dist: psutil>=5.7.0; extra == "optional"
Requires-Dist: gymnasium; extra == "optional"
Requires-Dist: lightsim2grid; extra == "optional"
Provides-Extra: gymnasium
Requires-Dist: gymnasium; extra == "gymnasium"
Provides-Extra: docs
Requires-Dist: numpydoc>=0.9.2; extra == "docs"
Requires-Dist: sphinx<7.0.0,>=2.4.4; extra == "docs"
Requires-Dist: sphinx-rtd-theme>=0.4.3; extra == "docs"
Requires-Dist: sphinxcontrib-trio>=1.1.0; extra == "docs"
Requires-Dist: autodocsumm>=0.1.13; extra == "docs"
Requires-Dist: gym>=0.17.2; extra == "docs"
Requires-Dist: gymnasium; extra == "docs"
Provides-Extra: plot
Requires-Dist: imageio; extra == "plot"
Provides-Extra: test
Requires-Dist: lightsim2grid; extra == "test"
Requires-Dist: numba; python_version <= "3.12" and extra == "test"
Requires-Dist: gymnasium; extra == "test"
Requires-Dist: nbconvert; extra == "test"
Requires-Dist: jinja2; extra == "test"
Requires-Dist: imageio; extra == "test"
Requires-Dist: plotly; extra == "test"
Requires-Dist: matplotlib; extra == "test"
Requires-Dist: seaborn; extra == "test"
Provides-Extra: chronix2grid
Requires-Dist: ChroniX2Grid>=1.2.0.post1; extra == "chronix2grid"
Requires-Dist: pypsa<0.25; extra == "chronix2grid"
Dynamic: license-file
